ES3F1_Lab_4/lab4_pcam/Zybo-Z7-20-pcam-filter/pcam_filter.srcs/sources_1/new/btn_ctrl.v
`timescale 1ns / 1ps
//////////////////////////////////////////////////////////////////////////////
// Button Controller — debounce, mode cycling, filter selection, LED output
//
// SW0:       branch select (0=single-pixel, 1=multi-pixel)
// BTN0–BTN2: select filter within active branch (one-hot, re-press deselects)
// BTN3:      cycle compositor mode (0→2→3→4→5→0)
// LED[0]:    branch_sel
// LED[1]:    any filter active
// LED[3:2]:  comp_mode[1:0]
//
// Software override: when sw_override=1, buttons ignored, register values used.
// Edge-overlay mode forces sobel on path B.
//////////////////////////////////////////////////////////////////////////////

module btn_ctrl #
(
    parameter CLK_FREQ_HZ = 148_500_000,
    parameter DEBOUNCE_MS = 20
)
(
    input  wire        clk,
    input  wire        n_rst,

    // Raw board I/O
    input  wire [3:0]  btn_raw,
    input  wire        sw0_raw,

    // Software override from AXI GPIO
    input  wire        sw_override,     // 1 = software controls all
    input  wire [2:0]  sw_comp_mode,
    input  wire [2:0]  sw_filter_sel_a, // 0=pass,1=bright,2=gamma,3=thresh,4=invert
    input  wire [2:0]  sw_filter_sel_b, // 0=pass,1=sobel,2=erode,3=dilate
    input  wire        sw_branch_sel,

    // Outputs to colour_change
    output reg  [3:0]  cc_btn,

    // Outputs to multi_filter_select
    output reg  [3:0]  mf_btn,

    // Outputs to compositor
    output reg  [2:0]  comp_mode,
    output reg         branch_sel,

    // LED outputs
    output reg  [3:0]  led
);

    // -------------------------------------------------------------------------
    // Debounce logic
    // -------------------------------------------------------------------------
    localparam DEBOUNCE_COUNT = (CLK_FREQ_HZ / 1000) * DEBOUNCE_MS;
    localparam CNT_WIDTH = $clog2(DEBOUNCE_COUNT + 1);

    reg [3:0] btn_sync1, btn_sync2;  // double-flop synchronizer
    reg [3:0] btn_stable;
    reg [3:0] btn_prev;
    reg [CNT_WIDTH-1:0] debounce_cnt [3:0];

    reg sw0_sync1, sw0_sync2;

    integer i;

    always @(posedge clk) begin
        if (!n_rst) begin
            btn_sync1 <= 4'b0;
            btn_sync2 <= 4'b0;
            btn_stable <= 4'b0;
            btn_prev <= 4'b0;
            sw0_sync1 <= 1'b0;
            sw0_sync2 <= 1'b0;
            for (i = 0; i < 4; i = i + 1)
                debounce_cnt[i] <= {CNT_WIDTH{1'b0}};
        end else begin
            // Synchronize inputs
            btn_sync1 <= btn_raw;
            btn_sync2 <= btn_sync1;
            sw0_sync1 <= sw0_raw;
            sw0_sync2 <= sw0_sync1;

            // Per-button debounce
            for (i = 0; i < 4; i = i + 1) begin
                if (btn_sync2[i] != btn_stable[i]) begin
                    if (debounce_cnt[i] >= DEBOUNCE_COUNT[CNT_WIDTH-1:0])  begin
                        btn_stable[i] <= btn_sync2[i];
                        debounce_cnt[i] <= {CNT_WIDTH{1'b0}};
                    end else begin
                        debounce_cnt[i] <= debounce_cnt[i] + 1;
                    end
                end else begin
                    debounce_cnt[i] <= {CNT_WIDTH{1'b0}};
                end
            end

            btn_prev <= btn_stable;
        end
    end

    // Rising edge detection on debounced buttons
    wire [3:0] btn_posedge;
    assign btn_posedge = btn_stable & ~btn_prev;

    // -------------------------------------------------------------------------
    // Mode cycling state machine (BTN3)
    // Sequence: 0 (full-filtered) → 2 (split) → 3 (wipe) → 4 (ROI) → 5 (overlay) → 0
    // -------------------------------------------------------------------------
    reg [2:0] hw_comp_mode;

    always @(posedge clk) begin
        if (!n_rst) begin
            hw_comp_mode <= 3'd0;
        end else if (btn_posedge[3]) begin
            case (hw_comp_mode)
                3'd0: hw_comp_mode <= 3'd2;
                3'd2: hw_comp_mode <= 3'd3;
                3'd3: hw_comp_mode <= 3'd4;
                3'd4: hw_comp_mode <= 3'd5;
                3'd5: hw_comp_mode <= 3'd0;
                default: hw_comp_mode <= 3'd0;
            endcase
        end
    end

    // -------------------------------------------------------------------------
    // Filter selection (BTN0–BTN2 within active branch)
    // One-hot with toggle: pressing active filter deselects it (passthrough)
    // Pressing a different filter selects it and deselects the previous
    // -------------------------------------------------------------------------
    reg [2:0] hw_filter_a;  // which filter in branch A (0=none/pass)
    reg [2:0] hw_filter_b;  // which filter in branch B (0=none/pass)

    always @(posedge clk) begin
        if (!n_rst) begin
            hw_filter_a <= 3'd0;
            hw_filter_b <= 3'd0;
        end else begin
            if (!sw0_sync2) begin
                // Branch A active: BTN0-2 control single-pixel filters
                if (btn_posedge[0])
                    hw_filter_a <= (hw_filter_a == 3'd1) ? 3'd0 : 3'd1;
                else if (btn_posedge[1])
                    hw_filter_a <= (hw_filter_a == 3'd2) ? 3'd0 : 3'd2;
                else if (btn_posedge[2])
                    hw_filter_a <= (hw_filter_a == 3'd3) ? 3'd0 : 3'd3;
            end else begin
                // Branch B active: BTN0-2 control multi-pixel filters
                if (btn_posedge[0])
                    hw_filter_b <= (hw_filter_b == 3'd1) ? 3'd0 : 3'd1;
                else if (btn_posedge[1])
                    hw_filter_b <= (hw_filter_b == 3'd2) ? 3'd0 : 3'd2;
                else if (btn_posedge[2])
                    hw_filter_b <= (hw_filter_b == 3'd3) ? 3'd0 : 3'd3;
            end
        end
    end

    // -------------------------------------------------------------------------
    // Output logic: software override vs hardware buttons
    // -------------------------------------------------------------------------
    reg [2:0] active_filter_a;
    reg [2:0] active_filter_b;
    reg [2:0] active_comp_mode;
    reg       active_branch;

    always @(*) begin
        if (sw_override) begin
            active_comp_mode = sw_comp_mode;
            active_filter_a  = sw_filter_sel_a;
            active_filter_b  = sw_filter_sel_b;
            active_branch    = sw_branch_sel;
        end else begin
            active_comp_mode = hw_comp_mode;
            active_filter_a  = hw_filter_a;
            active_filter_b  = hw_filter_b;
            active_branch    = sw0_sync2;
        end
    end

    // Map filter selection to btn[3:0] one-hot encoding for colour_change
    // colour_change uses: btn[0]=bright, btn[1]=gamma, btn[2]=thresh, btn[3]=invert
    always @(*) begin
        case (active_filter_a)
            3'd1:    cc_btn = 4'b0001;  // brightness
            3'd2:    cc_btn = 4'b0010;  // gamma
            3'd3:    cc_btn = 4'b0100;  // threshold
            3'd4:    cc_btn = 4'b1000;  // invert
            default: cc_btn = 4'b0000;  // passthrough
        endcase
    end

    // Map filter selection to btn[3:0] for multi_filter_select
    // multi_filter_select uses: btn[0]=sobel, btn[1]=erode, btn[2]=dilate
    // Special case: edge-overlay mode forces sobel
    always @(*) begin
        if (active_comp_mode == 3'd5) begin
            // Edge-overlay: force sobel on path B
            mf_btn = 4'b0001;
        end else begin
            case (active_filter_b)
                3'd1:    mf_btn = 4'b0001;  // sobel
                3'd2:    mf_btn = 4'b0010;  // erosion
                3'd3:    mf_btn = 4'b0100;  // dilation
                default: mf_btn = 4'b0000;  // passthrough
            endcase
        end
    end

    // Output compositor control
    always @(*) begin
        comp_mode  = active_comp_mode;
        branch_sel = active_branch;
    end

    // -------------------------------------------------------------------------
    // LED outputs (directly registered output reg — no intermediate wire/assign)
    // -------------------------------------------------------------------------
    wire any_filter_active;
    assign any_filter_active = (active_filter_a != 3'd0) || (active_filter_b != 3'd0);

    always @(posedge clk) begin
        if (!n_rst)
            led <= 4'b0000;
        else begin
            led[0] <= active_branch;
            led[1] <= any_filter_active;
            led[3:2] <= active_comp_mode[1:0];
        end
    end

endmodule

ES3F1_Lab_4/lab4_pcam/Zybo-Z7-20-pcam-filter/pcam_filter.srcs/sources_1/new/tb_btn_ctrl.v
`timescale 1ns / 1ps

module tb_btn_ctrl;

    parameter CLK_FREQ_HZ = 1_000_000;  // 1 MHz for fast sim (real is 148.5 MHz)
    parameter DEBOUNCE_MS = 1;           // 1ms debounce (1000 clocks at 1 MHz)
    parameter CLK_PERIOD = 1000;         // 1 us = 1000 ns

    reg        clk;
    reg        n_rst;
    reg  [3:0] btn_raw;
    reg        sw0_raw;
    reg        sw_override;
    reg  [2:0] sw_comp_mode;
    reg  [2:0] sw_filter_sel_a;
    reg  [2:0] sw_filter_sel_b;
    reg        sw_branch_sel;

    wire [3:0] cc_btn;
    wire [3:0] mf_btn;
    wire [2:0] comp_mode;
    wire       branch_sel;
    wire [3:0] led;

    // Instantiate DUT
    btn_ctrl #(
        .CLK_FREQ_HZ(CLK_FREQ_HZ),
        .DEBOUNCE_MS(DEBOUNCE_MS)
    ) dut (
        .clk(clk),
        .n_rst(n_rst),
        .btn_raw(btn_raw),
        .sw0_raw(sw0_raw),
        .sw_override(sw_override),
        .sw_comp_mode(sw_comp_mode),
        .sw_filter_sel_a(sw_filter_sel_a),
        .sw_filter_sel_b(sw_filter_sel_b),
        .sw_branch_sel(sw_branch_sel),
        .cc_btn(cc_btn),
        .mf_btn(mf_btn),
        .comp_mode(comp_mode),
        .branch_sel(branch_sel),
        .led(led)
    );

    // Clock
    initial clk = 0;
    always #(CLK_PERIOD/2) clk = ~clk;

    integer errors;

    // Task: press and release a button with debounce settling time
    task press_button;
        input [3:0] btn_mask;
        begin
            btn_raw = btn_mask;
            // Wait for debounce to settle (DEBOUNCE_MS * CLK_FREQ_HZ/1000 + margin)
            repeat (1500) @(posedge clk);
            btn_raw = 4'b0000;
            repeat (1500) @(posedge clk);
        end
    endtask

    initial begin
        $dumpfile("tb_btn_ctrl.vcd");
        $dumpvars(0, tb_btn_ctrl);

        errors = 0;

        // Init
        n_rst = 0;
        btn_raw = 4'b0000;
        sw0_raw = 0;
        sw_override = 0;
        sw_comp_mode = 3'd0;
        sw_filter_sel_a = 3'd0;
        sw_filter_sel_b = 3'd0;
        sw_branch_sel = 0;

        // Reset
        repeat (20) @(posedge clk);
        n_rst = 1;
        repeat (20) @(posedge clk);

        // -----------------------------------------------------------------
        // TEST 1: Initial state
        // -----------------------------------------------------------------
        $display("TEST 1: Initial state after reset");
        if (comp_mode !== 3'd0) begin
            $display("  FAIL: comp_mode = %d, expected 0", comp_mode);
            errors = errors + 1;
        end else $display("  PASS: comp_mode = 0");

        if (cc_btn !== 4'b0000) begin
            $display("  FAIL: cc_btn = %b, expected 0000", cc_btn);
            errors = errors + 1;
        end else $display("  PASS: cc_btn = 0000 (passthrough)");

        if (branch_sel !== 1'b0) begin
            $display("  FAIL: branch_sel = %b, expected 0", branch_sel);
            errors = errors + 1;
        end else $display("  PASS: branch_sel = 0 (path A)");

        // -----------------------------------------------------------------
        // TEST 2: BTN0 selects brightness (branch A active, sw0=0)
        // -----------------------------------------------------------------
        $display("\nTEST 2: BTN0 selects brightness in branch A");
        sw0_raw = 0;
        repeat (100) @(posedge clk);
        press_button(4'b0001);

        if (cc_btn !== 4'b0001) begin
            $display("  FAIL: cc_btn = %b, expected 0001", cc_btn);
            errors = errors + 1;
        end else $display("  PASS: cc_btn = 0001 (brightness)");

        // -----------------------------------------------------------------
        // TEST 3: BTN0 again toggles off (deselect)
        // -----------------------------------------------------------------
        $display("\nTEST 3: BTN0 again deselects (toggle off)");
        press_button(4'b0001);

        if (cc_btn !== 4'b0000) begin
            $display("  FAIL: cc_btn = %b, expected 0000", cc_btn);
            errors = errors + 1;
        end else $display("  PASS: cc_btn = 0000 (passthrough)");

        // -----------------------------------------------------------------
        // TEST 4: BTN1 selects gamma
        // -----------------------------------------------------------------
        $display("\nTEST 4: BTN1 selects gamma");
        press_button(4'b0010);

        if (cc_btn !== 4'b0010) begin
            $display("  FAIL: cc_btn = %b, expected 0010", cc_btn);
            errors = errors + 1;
        end else $display("  PASS: cc_btn = 0010 (gamma)");

        // -----------------------------------------------------------------
        // TEST 5: BTN2 selects threshold (replaces gamma — one-hot)
        // -----------------------------------------------------------------
        $display("\nTEST 5: BTN2 selects threshold (replaces gamma)");
        press_button(4'b0100);

        if (cc_btn !== 4'b0100) begin
            $display("  FAIL: cc_btn = %b, expected 0100", cc_btn);
            errors = errors + 1;
        end else $display("  PASS: cc_btn = 0100 (threshold)");

        // -----------------------------------------------------------------
        // TEST 6: Switch to branch B (sw0=1), BTN0 selects sobel
        // -----------------------------------------------------------------
        $display("\nTEST 6: Switch to branch B, BTN0 selects sobel");
        sw0_raw = 1;
        repeat (100) @(posedge clk);

        if (branch_sel !== 1'b1) begin
            $display("  FAIL: branch_sel = %b, expected 1", branch_sel);
            errors = errors + 1;
        end else $display("  PASS: branch_sel = 1 (path B)");

        press_button(4'b0001);

        if (mf_btn !== 4'b0001) begin
            $display("  FAIL: mf_btn = %b, expected 0001", mf_btn);
            errors = errors + 1;
        end else $display("  PASS: mf_btn = 0001 (sobel)");

        // -----------------------------------------------------------------
        // TEST 7: BTN3 cycles compositor mode (0 → 2)
        // -----------------------------------------------------------------
        $display("\nTEST 7: BTN3 cycles mode 0 -> 2");
        press_button(4'b1000);

        if (comp_mode !== 3'd2) begin
            $display("  FAIL: comp_mode = %d, expected 2", comp_mode);
            errors = errors + 1;
        end else $display("  PASS: comp_mode = 2 (split-screen)");

        // -----------------------------------------------------------------
        // TEST 8: BTN3 again (2 → 3)
        // -----------------------------------------------------------------
        $display("\nTEST 8: BTN3 cycles mode 2 -> 3");
        press_button(4'b1000);

        if (comp_mode !== 3'd3) begin
            $display("  FAIL: comp_mode = %d, expected 3", comp_mode);
            errors = errors + 1;
        end else $display("  PASS: comp_mode = 3 (wipe)");

        // -----------------------------------------------------------------
        // TEST 9: BTN3 cycles through 4, 5, back to 0
        // -----------------------------------------------------------------
        $display("\nTEST 9: Full mode cycle 3->4->5->0");
        press_button(4'b1000);
        if (comp_mode !== 3'd4) begin
            $display("  FAIL: expected 4, got %d", comp_mode);
            errors = errors + 1;
        end else $display("  PASS: mode = 4 (ROI)");

        press_button(4'b1000);
        if (comp_mode !== 3'd5) begin
            $display("  FAIL: expected 5, got %d", comp_mode);
            errors = errors + 1;
        end else $display("  PASS: mode = 5 (edge-overlay)");

        press_button(4'b1000);
        if (comp_mode !== 3'd0) begin
            $display("  FAIL: expected 0, got %d", comp_mode);
            errors = errors + 1;
        end else $display("  PASS: mode = 0 (full-filtered, wrapped)");

        // -----------------------------------------------------------------
        // TEST 10: Edge-overlay forces sobel on path B
        // -----------------------------------------------------------------
        $display("\nTEST 10: Edge-overlay mode forces mf_btn = sobel");
        // Set mode to 5
        press_button(4'b1000); // 0->2
        press_button(4'b1000); // 2->3
        press_button(4'b1000); // 3->4
        press_button(4'b1000); // 4->5

        if (mf_btn !== 4'b0001) begin
            $display("  FAIL: mf_btn = %b, expected 0001 (forced sobel)", mf_btn);
            errors = errors + 1;
        end else $display("  PASS: mf_btn = 0001 (sobel forced by overlay mode)");

        // -----------------------------------------------------------------
        // TEST 11: Software override
        // -----------------------------------------------------------------
        $display("\nTEST 11: Software override");
        sw_override = 1;
        sw_comp_mode = 3'd4;
        sw_filter_sel_a = 3'd3;
        sw_filter_sel_b = 3'd2;
        sw_branch_sel = 0;
        repeat (20) @(posedge clk);

        if (comp_mode !== 3'd4) begin
            $display("  FAIL: comp_mode = %d, expected 4", comp_mode);
            errors = errors + 1;
        end else $display("  PASS: comp_mode = 4 (from software)");

        if (cc_btn !== 4'b0100) begin
            $display("  FAIL: cc_btn = %b, expected 0100 (thresh from sw)", cc_btn);
            errors = errors + 1;
        end else $display("  PASS: cc_btn = 0100 (thresh from software)");

        if (branch_sel !== 1'b0) begin
            $display("  FAIL: branch_sel = %b, expected 0", branch_sel);
            errors = errors + 1;
        end else $display("  PASS: branch_sel = 0 (from software)");

        // -----------------------------------------------------------------
        // TEST 12: LED outputs
        // -----------------------------------------------------------------
        $display("\nTEST 12: LED outputs");
        if (led[0] !== branch_sel) begin
            $display("  FAIL: led[0] = %b, expected %b", led[0], branch_sel);
            errors = errors + 1;
        end else $display("  PASS: led[0] = branch_sel");

        if (led[1] !== 1'b1) begin
            $display("  FAIL: led[1] = %b, expected 1 (filter active)", led[1]);
            errors = errors + 1;
        end else $display("  PASS: led[1] = 1 (filter active)");

        // -----------------------------------------------------------------
        // Summary
        // -----------------------------------------------------------------
        $display("\n===========================================");
        if (errors == 0)
            $display(" ALL TESTS PASSED");
        else
            $display(" %0d TESTS FAILED", errors);
        $display("===========================================");
        $finish;
    end

endmodule

ES3F1_Lab_4/lab4_pcam/Zybo-Z7-20-pcam-filter/pcam_filter.srcs/sources_1/new/tb_btn_ctrl.vcd
$date
	Mon Apr 20 18:20:47 2026
$end
$version
	Icarus Verilog
$end
$timescale
	1ps
$end
$scope module tb_btn_ctrl $end
$var wire 4 ! mf_btn [3:0] $end
$var wire 4 " led [3:0] $end
$var wire 3 # comp_mode [2:0] $end
$var wire 4 $ cc_btn [3:0] $end
$var wire 1 % branch_sel $end
$var parameter 32 & CLK_FREQ_HZ $end
$var parameter 32 ' CLK_PERIOD $end
$var parameter 32 ( DEBOUNCE_MS $end
$var reg 4 ) btn_raw [3:0] $end
$var reg 1 * clk $end
$var reg 1 + n_rst $end
$var reg 1 , sw0_raw $end
$var reg 1 - sw_branch_sel $end
$var reg 3 . sw_comp_mode [2:0] $end
$var reg 3 / sw_filter_sel_a [2:0] $end
$var reg 3 0 sw_filter_sel_b [2:0] $end
$var reg 1 1 sw_override $end
$var integer 32 2 errors [31:0] $end
$scope module dut $end
$var wire 1 3 any_filter_active $end
$var wire 4 4 btn_posedge [3:0] $end
$var wire 4 5 btn_raw [3:0] $end
$var wire 1 * clk $end
$var wire 1 + n_rst $end
$var wire 1 , sw0_raw $end
$var wire 1 - sw_branch_sel $end
$var wire 3 6 sw_comp_mode [2:0] $end
$var wire 3 7 sw_filter_sel_a [2:0] $end
$var wire 3 8 sw_filter_sel_b [2:0] $end
$var wire 1 1 sw_override $end
$var parameter 32 9 CLK_FREQ_HZ $end
$var parameter 32 : CNT_WIDTH $end
$var parameter 64 ; DEBOUNCE_COUNT $end
$var parameter 32 < DEBOUNCE_MS $end
$var reg 1 = active_branch $end
$var reg 3 > active_comp_mode [2:0] $end
$var reg 3 ? active_filter_a [2:0] $end
$var reg 3 @ active_filter_b [2:0] $end
$var reg 1 % branch_sel $end
$var reg 4 A btn_prev [3:0] $end
$var reg 4 B btn_stable [3:0] $end
$var reg 4 C btn_sync1 [3:0] $end
$var reg 4 D btn_sync2 [3:0] $end
$var reg 4 E cc_btn [3:0] $end
$var reg 3 F comp_mode [2:0] $end
$var reg 3 G hw_comp_mode [2:0] $end
$var reg 3 H hw_filter_a [2:0] $end
$var reg 3 I hw_filter_b [2:0] $end
$var reg 4 J led [3:0] $end
$var reg 4 K mf_btn [3:0] $end
$var reg 1 L sw0_sync1 $end
$var reg 1 M sw0_sync2 $end
$var integer 32 N i [31:0] $end
$upscope $end
$scope task press_button $end
$var reg 4 O btn_mask [3:0] $end
$upscope $end
$upscope $end
$enddefinitions $end
$comment Show the parameter values. $end
$dumpall
b1 <
b1111101000 ;
b1010 :
b11110100001001000000 9
b1 (
b1111101000 '
b11110100001001000000 &
$end
#0
$dumpvars
bx O
bx N
xM
xL
bx K
bx J
bx I
bx H
bx G
bx F
bx E
bx D
bx C
bx B
bx A
bx @
bx ?
bx >
x=
b0 8
b0 7
b0 6
b0 5
bx 4
x3
b0 2
01
b0 0
b0 /
b0 .
0-
0,
0+
0*
b0 )
x%
bx $
bx #
bx "
bx !
$end
#500000
b0 $
b0 E
03
0%
b0 #
b0 F
b0 !
b0 K
b0 4
0=
b0 @
b0 ?
b0 >
0M
0L
b0 A
b0 B
b0 D
b0 C
b0 G
b0 I
b0 H
b0 "
b0 J
b100 N
1*
#1000000
0*
#1500000
b100 N
1*
#2000000
0*
#2500000
b100 N
1*
#3000000
0*
#3500000
b100 N
1*
#4000000
0*
#4500000
b100 N
1*
#5000000
0*
#5500000
b100 N
1*
#6000000
0*
#6500000
b100 N
1*
#7000000
0*
#7500000
b100 N
1*
#8000000
0*
#8500000
b100 N
1*
#9000000
0*
#9500000
b100 N
1*
#10000000
0*
#10500000
b100 N
1*
#11000000
0*
#11500000
b100 N
1*
#12000000
0*
#12500000
b100 N
1*
#13000000
0*
#13500000
b100 N
1*
#14000000
0*
#14500000
b100 N
1*
#15000000
0*
#15500000
b100 N
1*
#16000000
0*
#16500000
b100 N
1*
#17000000
0*
#17500000
b100 N
1*
#18000000
0*
#18500000
b100 N
1*
#19000000
0*
#19500000
1+
b100 N
1*
#20000000
0*
#20500000
b100 N
1*
#21000000
0*
#21500000
b100 N
1*
#22000000
0*
#22500000
b100 N
1*
#23000000
0*
#23500000
b100 N
1*
#24000000
0*
#24500000
b100 N
1*
#25000000
0*
#25500000
b100 N
1*
#26000000
0*
#26500000
b100 N
1*
#27000000
0*
#27500000
b100 N
1*
#28000000
0*
#28500000
b100 N
1*
#29000000
0*
#29500000
b100 N
1*
#30000000
0*
#30500000
b100 N
1*
#31000000
0*
#31500000
b100 N
1*
#32000000
0*
#32500000
b100 N
1*
#33000000
0*
#33500000
b100 N
1*
#34000000
0*
#34500000
b100 N
1*
#35000000
0*
#35500000
b100 N
1*
#36000000
0*
#36500000
b100 N
1*
#37000000
0*
#37500000
b100 N
1*
#38000000
0*
#38500000
b100 N
1*
#39000000
0*
#39500000
b100 N
1*
#40000000
0*
#40500000
b100 N
1*
#41000000
0*
#41500000
b100 N
1*
#42000000
0*
#42500000
b100 N
1*
#43000000
0*
#43500000
b100 N
1*
#44000000
0*
#44500000
b100 N
1*
#45000000
0*
#45500000
b100 N
1*
#46000000
0*
#46500000
b100 N
1*
#47000000
0*
#47500000
b100 N
1*
#48000000
0*
#48500000
b100 N
1*
#49000000
0*
#49500000
b100 N
1*
#50000000
0*
#50500000
b100 N
1*
#51000000
0*
#51500000
b100 N
1*
#52000000
0*
#52500000
b100 N
1*
#53000000
0*
#53500000
b100 N
1*
#54000000
0*
#54500000
b100 N
1*
#55000000
0*
#55500000
b100 N
1*
#56000000
0*
#56500000
b100 N
1*
#57000000
0*
#57500000
b100 N
1*
#58000000
0*
#58500000
b100 N
1*
#59000000
0*
#59500000
b100 N
1*
#60000000
0*
#60500000
b100 N
1*
#61000000
0*
#61500000
b100 N
1*
#62000000
0*
#62500000
b100 N
1*
#63000000
0*
#63500000
b100 N
1*
#64000000
0*
#64500000
b100 N
1*
#65000000
0*
#65500000
b100 N
1*
#66000000
0*
#66500000
b100 N
1*
#67000000
0*
#67500000
b100 N
1*
#68000000
0*
#68500000
b100 N
1*
#69000000
0*
#69500000
b100 N
1*
#70000000
0*
#70500000
b100 N
1*
#71000000
0*
#71500000
b100 N
1*
#72000000
0*
#72500000
b100 N
1*
#73000000
0*
#73500000
b100 N
1*
#74000000
0*
#74500000
b100 N
1*
#75000000
0*
#75500000
b100 N
1*
#76000000
0*
#76500000
b100 N
1*
#77000000
0*
#77500000
b100 N
1*
#78000000
0*
#78500000
b100 N
1*
#79000000
0*
#79500000
b100 N
1*
#80000000
0*
#80500000
b100 N
1*
#81000000
0*
#81500000
b100 N
1*
#82000000
0*
#82500000
b100 N
1*
#83000000
0*
#83500000
b100 N
1*
#84000000
0*
#84500000
b100 N
1*
#85000000
0*
#85500000
b100 N
1*
#86000000
0*
#86500000
b100 N
1*
#87000000
0*
#87500000
b100 N
1*
#88000000
0*
#88500000
b100 N
1*
#89000000
0*
#89500000
b100 N
1*
#90000000
0*
#90500000
b100 N
1*
#91000000
0*
#91500000
b100 N
1*
#92000000
0*
#92500000
b100 N
1*
#93000000
0*
#93500000
b100 N
1*
#94000000
0*
#94500000
b100 N
1*
#95000000
0*
#95500000
b100 N
1*
#96000000
0*
#96500000
b100 N
1*
#97000000
0*
#97500000
b100 N
1*
#98000000
0*
#98500000
b100 N
1*
#99000000
0*
#99500000
b100 N
1*
#100000000
0*
#100500000
b100 N
1*
#101000000
0*
#101500000
b100 N
1*
#102000000
0*
#102500000
b100 N
1*
#103000000
0*
#103500000
b100 N
1*
#104000000
0*
#104500000
b100 N
1*
#105000000
0*
#105500000
b100 N
1*
#106000000
0*
#106500000
b100 N
1*
#107000000
0*
#107500000
b100 N
1*
#108000000
0*
#108500000
b100 N
1*
#109000000
0*
#109500000
b100 N
1*
#110000000
0*
#110500000
b100 N
1*
#111000000
0*
#111500000
b100 N
1*
#112000000
0*
#112500000
b100 N
1*
#113000000
0*
#113500000
b100 N
1*
#114000000
0*
#114500000
b100 N
1*
#115000000
0*
#115500000
b100 N
1*
#116000000
0*
#116500000
b100 N
1*
#117000000
0*
#117500000
b100 N
1*
#118000000
0*
#118500000
b100 N
1*
#119000000
0*
#119500000
b100 N
1*
#120000000
0*
#120500000
b100 N
1*
#121000000
0*
#121500000
b100 N
1*
#122000000
0*
#122500000
b100 N
1*
#123000000
0*
#123500000
b100 N
1*
#124000000
0*
#124500000
b100 N
1*
#125000000
0*
#125500000
b100 N
1*
#126000000
0*
#126500000
b100 N
1*
#127000000
0*
#127500000
b100 N
1*
#128000000
0*
#128500000
b100 N
1*
#129000000
0*
#129500000
b100 N
1*
#130000000
0*
#130500000
b100 N
1*
#131000000
0*
#131500000
b100 N
1*
#132000000
0*
#132500000
b100 N
1*
#133000000
0*
#133500000
b100 N
1*
#134000000
0*
#134500000
b100 N
1*
#135000000
0*
#135500000
b100 N
1*
#136000000
0*
#136500000
b100 N
1*
#137000000
0*
#137500000
b100 N
1*
#138000000
0*
#138500000
b100 N
1*
#139000000
0*
#139500000
b1 )
b1 5
b1 O
b100 N
1*
#140000000
0*
#140500000
b1 C
b100 N
1*
#141000000
0*
#141500000
b1 D
b100 N
1*
#142000000
0*
#142500000
b100 N
1*
#143000000
0*
#143500000
b100 N
1*
#144000000
0*
#144500000
b100 N
1*
#145000000
0*
#145500000
b100 N
1*
#146000000
0*
#146500000
b100 N
1*
#147000000
0*
#147500000
b100 N
1*
#148000000
0*
#148500000
b100 N
1*
#149000000
0*
#149500000
b100 N
1*
#150000000
0*
#150500000
b100 N
1*
#151000000
0*
#151500000
b100 N
1*
#152000000
0*
#152500000
b100 N
1*
#153000000
0*
#153500000
b100 N
1*
#154000000
0*
#154500000
b100 N
1*
#155000000
0*
#155500000
b100 N
1*
#156000000
0*
#156500000
b100 N
1*
#157000000
0*
#157500000
b100 N
1*
#158000000
0*
#158500000
b100 N
1*
#159000000
0*
#159500000
b100 N
1*
#160000000
0*
#160500000
b100 N
1*
#161000000
0*
#161500000
b100 N
1*
#162000000
0*
#162500000
b100 N
1*
#163000000
0*
#163500000
b100 N
1*
#164000000
0*
#164500000
b100 N
1*
#165000000
0*
#165500000
b100 N
1*
#166000000
0*
#166500000
b100 N
1*
#167000000
0*
#167500000
b100 N
1*
#168000000
0*
#168500000
b100 N
1*
#169000000
0*
#169500000
b100 N
1*
#170000000
0*
#170500000
b100 N
1*
#171000000
0*
#171500000
b100 N
1*
#172000000
0*
#172500000
b100 N
1*
#173000000
0*
#173500000
b100 N
1*
#174000000
0*
#174500000
b100 N
1*
#175000000
0*
#175500000
b100 N
1*
#176000000
0*
#176500000
b100 N
1*
#177000000
0*
#177500000
b100 N
1*
#178000000
0*
#178500000
b100 N
1*
#179000000
0*
#179500000
b100 N
1*
#180000000
0*
#180500000
b100 N
1*
#181000000
0*
#181500000
b100 N
1*
#182000000
0*
#182500000
b100 N
1*
#183000000
0*
#183500000
b100 N
1*
#184000000
0*
#184500000
b100 N
1*
#185000000
0*
#185500000
b100 N
1*
#186000000
0*
#186500000
b100 N
1*
#187000000
0*
#187500000
b100 N
1*
#188000000
0*
#188500000
b100 N
1*
#189000000
0*
#189500000
b100 N
1*
#190000000
0*
#190500000
b100 N
1*
#191000000
0*
#191500000
b100 N
1*
#192000000
0*
#192500000
b100 N
1*
#193000000
0*
#193500000
b100 N
1*
#194000000
0*
#194500000
b100 N
1*
#195000000
0*
#195500000
b100 N
1*
#196000000
0*
#196500000
b100 N
1*
#197000000
0*
#197500000
b100 N
1*
#198000000
0*
#198500000
b100 N
1*
#199000000
0*
#199500000
b100 N
1*
#200000000
0*
#200500000
b100 N
1*
#201000000
0*
#201500000
b100 N
1*
#202000000
0*
#202500000
b100 N
1*
#203000000
0*
#203500000
b100 N
1*
#204000000
0*
#204500000
b100 N
1*
#205000000
0*
#205500000
b100 N
1*
#206000000
0*
#206500000
b100 N
1*
#207000000
0*
#207500000
b100 N
1*
#208000000
0*
#208500000
b100 N
1*
#209000000
0*
#209500000
b100 N
1*
#210000000
0*
#210500000
b100 N
1*
#211000000
0*
#211500000
b100 N
1*
#212000000
0*
#212500000
b100 N
1*
#213000000
0*
#213500000
b100 N
1*
#214000000
0*
#214500000
b100 N
1*
#215000000
0*
#215500000
b100 N
1*
#216000000
0*
#216500000
b100 N
1*
#217000000
0*
#217500000
b100 N
1*
#218000000
0*
#218500000
b100 N
1*
#219000000
0*
#219500000
b100 N
1*
#220000000
0*
#220500000
b100 N
1*
#221000000
0*
#221500000
b100 N
1*
#222000000
0*
#222500000
b100 N
1*
#223000000
0*
#223500000
b100 N
1*
#224000000
0*
#224500000
b100 N
1*
#225000000
0*
#225500000
b100 N
1*
#226000000
0*
#226500000
b100 N
1*
#227000000
0*
#227500000
b100 N
1*
#228000000
0*
#228500000
b100 N
1*
#229000000
0*
#229500000
b100 N
1*
#230000000
0*
#230500000
b100 N
1*
#231000000
0*
#231500000
b100 N
1*
#232000000
0*
#232500000
b100 N
1*
#233000000
0*
#233500000
b100 N
1*
#234000000
0*
#234500000
b100 N
1*
#235000000
0*
#235500000
b100 N
1*
#236000000
0*
#236500000
b100 N
1*
#237000000
0*
#237500000
b100 N
1*
#238000000
0*
#238500000
b100 N
1*
#239000000
0*
#239500000
b100 N
1*
#240000000
0*
#240500000
b100 N
1*
#241000000
0*
#241500000
b100 N
1*
#242000000
0*
#242500000
b100 N
1*
#243000000
0*
#243500000
b100 N
1*
#244000000
0*
#244500000
b100 N
1*
#245000000
0*
#245500000
b100 N
1*
#246000000
0*
#246500000
b100 N
1*
#247000000
0*
#247500000
b100 N
1*
#248000000
0*
#248500000
b100 N
1*
#249000000
0*
#249500000
b100 N
1*
#250000000
0*
#250500000
b100 N
1*
#251000000
0*
